{
    "sessions" : "sessionschema",
    "acoustic_tasks": "acoustictaskschema",
    "recordings": "recordingschema",
    "participant": "subjectparticipantbasicinformationschema",
    "eligibility": "subjectparticipanteligiblestudiesschema",
    "enrollment": "enrollmentformschema",
    "vocalFoldParalysis": "dvoicevocalfoldparalysisschema",
    "laryngealdystonia": "dvoicelaryngealdystoniaschema",
    "precancerouseLesions": "dvoiceprecancerouslesionsschema",
    "laryngealcancer": "dvoicelaryngealcancerschema",
    "benignLesion": "dvoicebenignlesionsschema",
    "bipolar": "dmoodbipolardisorderschema",
    "depression": "dmooddepressionormajordepressivedisorderschema",
    "airwaystenosis": "drespairwaystenosisschema",
    "alzheimers": "dneuroalzheimersdiseasemildcognitiveimpairmeschema",
    "parkinsons": "dneuroparkinsonsdiseaseschema",
    "als": "dneuroamyotrophiclateralsclerosisalsschema",
    "demographics": "qgenericdemographicsschema",
    "confounders": "qgenericconfoundersschema",
    "gad7": "qgenericgad7anxietyschema",
    "phq9": "qgenericpatienthealthquestionnaire9schema",
    "voicePerception": "qgenericvoiceperceptionschema",
    "vhi10": "qgenericvoicehandicapindexvhi10schema",
    "panas": "qmoodpanasschema",
    "customAffectScale": "qmoodcustomaffectscaleschema",
    "dsm5": "qmooddsm5adultschema",
    "ptsd": "qmoodptsdadultschema",
    "adhd": "qmoodadhdadultschema",
    "dyspnea": "qrespdyspneaindexdischema",
    "leicester": "qrespleicestercoughquestionnairelcqschema",
    "voiceSeverity": "qvoicevoiceproblemseverityschema",
    "winograd": "qneurowinogradschemasschema",
    "stroop": "qneurowordcolorstroopschema",
    "vocab": "qneuroproductivevocabularyschema",
    "random": "qneurorandomitemgenerationschema"
}