{
    "d_voice_precancerous_lesions_schema": {
        "description": "Measures features of precancerous lesions.",
        "url": "https://raw.githubusercontent.com/sensein/b2ai-redcap2rs/24cbb461c2ff6556f047dd4bc1275b4b08d52eb8/activities/d_voice_precancerous_lesions/d_voice_precancerous_lesions_schema",
        "data_elements": {
            "diagnois_pl_gsd_ls": {
                "description": "Indicates if the participant has a precancerous vocal fold lesion confirmed by laryngoscopy or stroboscopy.",
                "question": {
                    "en": "Does the patient have a precancerous vocal fold lesion confirmed by laryngoscopy/stroboscopy?"
                },
                "datatype": [
                    "xsd:string"
                ],
                "choices": [
                    {
                        "name": {
                            "en": "Yes"
                        },
                        "value": "yes"
                    },
                    {
                        "name": {
                            "en": "No"
                        },
                        "value": "no"
                    },
                    {
                        "name": {
                            "en": "Not certain"
                        },
                        "value": "notCertain"
                    }
                ],
                "termURL": "https://raw.githubusercontent.com/sensein/b2ai-redcap2rs/24cbb461c2ff6556f047dd4bc1275b4b08d52eb8/activities/d_voice_precancerous_lesions/items/diagnois_pl_gsd_ls",
                "valueType": [
                    "xsd:string"
                ]
            },
            "diagnois_pl_gsd_bp": {
                "description": "Indicates if the participant has a precancerous vocal fold lesion confirmed by biopsy or pathology.",
                "question": {
                    "en": "Does the patient have a precancerous vocal fold lesion confirmed by biopsy/pathology?"
                },
                "datatype": [
                    "xsd:string"
                ],
                "choices": [
                    {
                        "name": {
                            "en": "Yes"
                        },
                        "value": "yes"
                    },
                    {
                        "name": {
                            "en": "No"
                        },
                        "value": "no"
                    },
                    {
                        "name": {
                            "en": "Not certain"
                        },
                        "value": "notCertain"
                    }
                ],
                "termURL": "https://raw.githubusercontent.com/sensein/b2ai-redcap2rs/24cbb461c2ff6556f047dd4bc1275b4b08d52eb8/activities/d_voice_precancerous_lesions/items/diagnois_pl_gsd_bp",
                "valueType": [
                    "xsd:string"
                ]
            },
            "diagnosis_pl_ds___keratosis": {
                "description": "Indicates if the participant has been diagnosed with keratosis."
            },
            "diagnosis_pl_ds___leukoplakia": {
                "description": "Indicates if the participant has been diagnosed with leukoplakia."
            },
            "diagnosis_pl_ds___erythroplakia": {
                "description": "Indicates if the participant has been diagnosed with erythroplakia."
            },
            "diagnosis_pl_ds___other": {
                "description": "Indicates if the participant has been diagnosed with another precancerous lesion."
            },
            "diagnosis_pl_ds_l": {
                "description": "Indicates if the participant has leukoplakia.",
                "question": {
                    "en": "Leukoplakia"
                },
                "datatype": [
                    "xsd:string"
                ],
                "choices": [
                    {
                        "name": {
                            "en": "With dysplasia"
                        },
                        "value": "withDysplasia"
                    },
                    {
                        "name": {
                            "en": "Without dysplasia"
                        },
                        "value": "withoutDysplasia"
                    }
                ],
                "termURL": "https://raw.githubusercontent.com/sensein/b2ai-redcap2rs/24cbb461c2ff6556f047dd4bc1275b4b08d52eb8/activities/d_voice_precancerous_lesions/items/diagnosis_pl_ds_l",
                "valueType": [
                    "xsd:string"
                ]
            },
            "diagnosis_pl_ds_l_wd_g": {
                "description": "Indicates if the participant has leukoplakia with dysplasia.",
                "question": {
                    "en": "Leukoplakia with dysplasia"
                },
                "datatype": [
                    "xsd:string"
                ],
                "choices": [
                    {
                        "name": {
                            "en": "Low grade"
                        },
                        "value": "lowGrade"
                    },
                    {
                        "name": {
                            "en": "Moderate grade"
                        },
                        "value": "moderateGrade"
                    },
                    {
                        "name": {
                            "en": "High grade"
                        },
                        "value": "highGrade"
                    }
                ],
                "termURL": "https://raw.githubusercontent.com/sensein/b2ai-redcap2rs/24cbb461c2ff6556f047dd4bc1275b4b08d52eb8/activities/d_voice_precancerous_lesions/items/diagnosis_pl_ds_l_wd_g",
                "valueType": [
                    "xsd:string"
                ]
            },
            "diagnosis_pl_ds_e": {
                "description": "Indicates if the participant has erythroplakia.",
                "question": {
                    "en": "Erythroplakia"
                },
                "datatype": [
                    "xsd:string"
                ],
                "choices": [
                    {
                        "name": {
                            "en": "With dysplasia"
                        },
                        "value": "withDysplasia"
                    },
                    {
                        "name": {
                            "en": "Without dysplasia"
                        },
                        "value": "withoutDysplasia"
                    }
                ],
                "termURL": "https://raw.githubusercontent.com/sensein/b2ai-redcap2rs/24cbb461c2ff6556f047dd4bc1275b4b08d52eb8/activities/d_voice_precancerous_lesions/items/diagnosis_pl_ds_e",
                "valueType": [
                    "xsd:string"
                ]
            },
            "diagnosis_pl_ds_e_wd_g": {
                "description": "Indicates if the participant has erythroplakia with dysplasia.",
                "question": {
                    "en": "Erythroplakia with dysplasia"
                },
                "datatype": [
                    "xsd:string"
                ],
                "choices": [
                    {
                        "name": {
                            "en": "Low grade"
                        },
                        "value": "lowGrade"
                    },
                    {
                        "name": {
                            "en": "Moderate grade"
                        },
                        "value": "moderateGrade"
                    },
                    {
                        "name": {
                            "en": "High grade"
                        },
                        "value": "highGrade"
                    }
                ],
                "termURL": "https://raw.githubusercontent.com/sensein/b2ai-redcap2rs/24cbb461c2ff6556f047dd4bc1275b4b08d52eb8/activities/d_voice_precancerous_lesions/items/diagnosis_pl_ds_e_wd_g",
                "valueType": [
                    "xsd:string"
                ]
            },
            "diagnosis_pl_etiology___past_or_present_smoking": {
                "description": "Indicates if the participant has a history of smoking as a risk factor for their precancerous lesion."
            },
            "diagnosis_pl_etiology___laryngopharyngeal_reflux": {
                "description": "Indicates if the participant has laryngopharyngeal reflux as a risk factor for their precancerous lesion."
            },
            "diagnosis_pl_etiology___other_irritants": {
                "description": "Indicates if the participant has other irritants as risk factors for their precancerous lesion."
            },
            "diagnosis_pl_ds_ll___right_vocal_fold": {
                "description": "Indicates if the participant's lesion is located on the right vocal fold."
            },
            "diagnosis_pl_ds_ll___left_vocal_fold": {
                "description": "Indicates if the participant's lesion is located on the left vocal fold."
            },
            "diagnosis_pl_ds_ll___both_vocal_folds": {
                "description": "Indicates if the participant's lesion is located on both vocal folds."
            },
            "diagnosis_pl_ds_ll___ventricular_folds": {
                "description": "Indicates if the participant's lesion is located on the ventricular folds."
            },
            "diagnosis_pl_ds_ll___subglottal_areas": {
                "description": "Indicates if the participant's lesion is located in the subglottal areas."
            },
            "diagnosis_pl_degree_os_1": {
                "description": "Indicates the overall severity of the participant’s precancerous lesion.",
                "question": {
                    "en": "Overall Severity"
                },
                "datatype": [
                    "xsd:string"
                ],
                "choices": [
                    {
                        "name": {
                            "en": "MI"
                        },
                        "value": "MI"
                    },
                    {
                        "name": {
                            "en": "MO"
                        },
                        "value": "MO"
                    },
                    {
                        "name": {
                            "en": "SE"
                        },
                        "value": "SE"
                    }
                ],
                "termURL": "https://raw.githubusercontent.com/sensein/b2ai-redcap2rs/24cbb461c2ff6556f047dd4bc1275b4b08d52eb8/activities/d_voice_precancerous_lesions/items/diagnosis_pl_degree_os_1",
                "maxValue": 100,
                "minValue": 0,
                "valueType": [
                    "xsd:string"
                ]
            },
            "diagnosis_pl_degree_os_2": {
                "description": "Indicates an alternative measure of the overall severity of the participant’s precancerous lesion.",
                "question": {
                    "en": "Overall Severity"
                },
                "datatype": [
                    "xsd:string"
                ],
                "choices": [
                    {
                        "name": {
                            "en": "Consistent"
                        },
                        "value": "consistent"
                    },
                    {
                        "name": {
                            "en": "Intermittent"
                        },
                        "value": "intermittent"
                    }
                ],
                "termURL": "https://raw.githubusercontent.com/sensein/b2ai-redcap2rs/24cbb461c2ff6556f047dd4bc1275b4b08d52eb8/activities/d_voice_precancerous_lesions/items/diagnosis_pl_degree_os_2",
                "valueType": [
                    "xsd:string"
                ]
            },
            "diagnosis_pl_degree_r_1": {
                "description": "Indicates the roughness of the participant’s voice due to the precancerous lesion.",
                "question": {
                    "en": "Roughness"
                },
                "datatype": [
                    "xsd:string"
                ],
                "choices": [
                    {
                        "name": {
                            "en": "MI"
                        },
                        "value": "MI"
                    },
                    {
                        "name": {
                            "en": "MO"
                        },
                        "value": "MO"
                    },
                    {
                        "name": {
                            "en": "SE"
                        },
                        "value": "SE"
                    }
                ],
                "termURL": "https://raw.githubusercontent.com/sensein/b2ai-redcap2rs/24cbb461c2ff6556f047dd4bc1275b4b08d52eb8/activities/d_voice_precancerous_lesions/items/diagnosis_pl_degree_r_1",
                "maxValue": 100,
                "minValue": 0,
                "valueType": [
                    "xsd:string"
                ]
            },
            "diagnosis_pl_degree_r_2": {
                "description": "Indicates an alternative measure of the roughness of the participant’s voice due to the precancerous lesion.",
                "question": {
                    "en": "Roughness"
                },
                "datatype": [
                    "xsd:string"
                ],
                "choices": [
                    {
                        "name": {
                            "en": "Consistent"
                        },
                        "value": "consistent"
                    },
                    {
                        "name": {
                            "en": "Intermittent"
                        },
                        "value": "intermittent"
                    }
                ],
                "termURL": "https://raw.githubusercontent.com/sensein/b2ai-redcap2rs/24cbb461c2ff6556f047dd4bc1275b4b08d52eb8/activities/d_voice_precancerous_lesions/items/diagnosis_pl_degree_r_2",
                "valueType": [
                    "xsd:string"
                ]
            },
            "diagnosis_pl_degree_b_1": {
                "description": "Indicates the breathiness of the participant’s voice due to the precancerous lesion.",
                "question": {
                    "en": "Breathiness"
                },
                "datatype": [
                    "xsd:string"
                ],
                "choices": [
                    {
                        "name": {
                            "en": "MI"
                        },
                        "value": "MI"
                    },
                    {
                        "name": {
                            "en": "MO"
                        },
                        "value": "MO"
                    },
                    {
                        "name": {
                            "en": "SE"
                        },
                        "value": "SE"
                    }
                ],
                "termURL": "https://raw.githubusercontent.com/sensein/b2ai-redcap2rs/24cbb461c2ff6556f047dd4bc1275b4b08d52eb8/activities/d_voice_precancerous_lesions/items/diagnosis_pl_degree_b_1",
                "maxValue": 100,
                "minValue": 0,
                "valueType": [
                    "xsd:string"
                ]
            },
            "diagnosis_pl_degree_b_2": {
                "description": "Indicates an alternative measure of the breathiness of the participant’s voice due to the precancerous lesion.",
                "question": {
                    "en": "Breathiness"
                },
                "datatype": [
                    "xsd:string"
                ],
                "choices": [
                    {
                        "name": {
                            "en": "Consistent"
                        },
                        "value": "consistent"
                    },
                    {
                        "name": {
                            "en": "Intermittent"
                        },
                        "value": "intermittent"
                    }
                ],
                "termURL": "https://raw.githubusercontent.com/sensein/b2ai-redcap2rs/24cbb461c2ff6556f047dd4bc1275b4b08d52eb8/activities/d_voice_precancerous_lesions/items/diagnosis_pl_degree_b_2",
                "valueType": [
                    "xsd:string"
                ]
            },
            "diagnosis_pl_degree_s_1": {
                "description": "Indicates the strain in the participant’s voice due to the precancerous lesion.",
                "question": {
                    "en": "Strain"
                },
                "datatype": [
                    "xsd:string"
                ],
                "choices": [
                    {
                        "name": {
                            "en": "MI"
                        },
                        "value": "MI"
                    },
                    {
                        "name": {
                            "en": "MO"
                        },
                        "value": "MO"
                    },
                    {
                        "name": {
                            "en": "SE"
                        },
                        "value": "SE"
                    }
                ],
                "termURL": "https://raw.githubusercontent.com/sensein/b2ai-redcap2rs/24cbb461c2ff6556f047dd4bc1275b4b08d52eb8/activities/d_voice_precancerous_lesions/items/diagnosis_pl_degree_s_1",
                "maxValue": 100,
                "minValue": 0,
                "valueType": [
                    "xsd:string"
                ]
            },
            "diagnosis_pl_degree_s_2": {
                "description": "Indicates an alternative measure of the strain in the participant’s voice due to the precancerous lesion.",
                "question": {
                    "en": "Strain"
                },
                "datatype": [
                    "xsd:string"
                ],
                "choices": [
                    {
                        "name": {
                            "en": "Consistent"
                        },
                        "value": "consistent"
                    },
                    {
                        "name": {
                            "en": "Intermittent"
                        },
                        "value": "intermittent"
                    }
                ],
                "termURL": "https://raw.githubusercontent.com/sensein/b2ai-redcap2rs/24cbb461c2ff6556f047dd4bc1275b4b08d52eb8/activities/d_voice_precancerous_lesions/items/diagnosis_pl_degree_s_2",
                "valueType": [
                    "xsd:string"
                ]
            },
            "diagnosis_pl_degree_p_1": {
                "description": "Indicates the pitch of the participant’s voice due to the precancerous lesion.",
                "question": {
                    "en": "Pitch"
                },
                "datatype": [
                    "xsd:string"
                ],
                "choices": [
                    {
                        "name": {
                            "en": "MI"
                        },
                        "value": "MI"
                    },
                    {
                        "name": {
                            "en": "MO"
                        },
                        "value": "MO"
                    },
                    {
                        "name": {
                            "en": "SE"
                        },
                        "value": "SE"
                    }
                ],
                "termURL": "https://raw.githubusercontent.com/sensein/b2ai-redcap2rs/24cbb461c2ff6556f047dd4bc1275b4b08d52eb8/activities/d_voice_precancerous_lesions/items/diagnosis_pl_degree_p_1",
                "maxValue": 100,
                "minValue": 0,
                "valueType": [
                    "xsd:string"
                ]
            },
            "diagnosis_pl_degree_p_2": {
                "description": "Indicates an alternative measure of the pitch of the participant’s voice due to the precancerous lesion.",
                "question": {
                    "en": "Pitch"
                },
                "datatype": [
                    "xsd:string"
                ],
                "choices": [
                    {
                        "name": {
                            "en": "Consistent"
                        },
                        "value": "consistent"
                    },
                    {
                        "name": {
                            "en": "Intermittent"
                        },
                        "value": "intermittent"
                    }
                ],
                "termURL": "https://raw.githubusercontent.com/sensein/b2ai-redcap2rs/24cbb461c2ff6556f047dd4bc1275b4b08d52eb8/activities/d_voice_precancerous_lesions/items/diagnosis_pl_degree_p_2",
                "valueType": [
                    "xsd:string"
                ]
            },
            "diagnosis_pl_degree_l_1": {
                "description": "Indicates the loudness of the participant’s voice due to the precancerous lesion.",
                "question": {
                    "en": "Loudness"
                },
                "datatype": [
                    "xsd:string"
                ],
                "choices": [
                    {
                        "name": {
                            "en": "MI"
                        },
                        "value": "MI"
                    },
                    {
                        "name": {
                            "en": "MO"
                        },
                        "value": "MO"
                    },
                    {
                        "name": {
                            "en": "SE"
                        },
                        "value": "SE"
                    }
                ],
                "termURL": "https://raw.githubusercontent.com/sensein/b2ai-redcap2rs/24cbb461c2ff6556f047dd4bc1275b4b08d52eb8/activities/d_voice_precancerous_lesions/items/diagnosis_pl_degree_l_1",
                "maxValue": 100,
                "minValue": 0,
                "valueType": [
                    "xsd:string"
                ]
            },
            "diagnosis_pl_degree_l_2": {
                "description": "Indicates an alternative measure of the loudness of the participant’s voice due to the precancerous lesion.",
                "question": {
                    "en": "Loudness"
                },
                "datatype": [
                    "xsd:string"
                ],
                "choices": [
                    {
                        "name": {
                            "en": "Consistent"
                        },
                        "value": "consistent"
                    },
                    {
                        "name": {
                            "en": "Intermittent"
                        },
                        "value": "intermittent"
                    }
                ],
                "termURL": "https://raw.githubusercontent.com/sensein/b2ai-redcap2rs/24cbb461c2ff6556f047dd4bc1275b4b08d52eb8/activities/d_voice_precancerous_lesions/items/diagnosis_pl_degree_l_2",
                "valueType": [
                    "xsd:string"
                ]
            },
            "diagnosis_pl_degree_comments": {
                "description": "Provides additional comments about the resonance of the participant’s voice due to the precancerous lesion.",
                "question": {
                    "en": "Comments about resonance"
                },
                "datatype": [
                    "xsd:string"
                ],
                "choices": [
                    {
                        "name": {
                            "en": "Normal"
                        },
                        "value": "normal"
                    },
                    {
                        "name": {
                            "en": "Other"
                        },
                        "value": "other"
                    }
                ],
                "termURL": "https://raw.githubusercontent.com/sensein/b2ai-redcap2rs/24cbb461c2ff6556f047dd4bc1275b4b08d52eb8/activities/d_voice_precancerous_lesions/items/diagnosis_pl_degree_comments",
                "valueType": [
                    "xsd:string"
                ]
            },
            "diagnosis_pl_treatment": {
                "description": "Indicates if the participant has undergone any treatment for their precancerous lesion.",
                "question": {
                    "en": "Has the patient undergone any treatment for this condition?"
                },
                "datatype": [
                    "xsd:string"
                ],
                "choices": [
                    {
                        "name": {
                            "en": "Yes"
                        },
                        "value": "yes"
                    },
                    {
                        "name": {
                            "en": "No"
                        },
                        "value": "no"
                    }
                ],
                "termURL": "https://raw.githubusercontent.com/sensein/b2ai-redcap2rs/24cbb461c2ff6556f047dd4bc1275b4b08d52eb8/activities/d_voice_precancerous_lesions/items/diagnosis_pl_treatment",
                "valueType": [
                    "xsd:string"
                ]
            },
            "diagnosis_pl_treatment_select___surveillance_only": {
                "description": "Indicates if the participant is under surveillance only as treatment for their precancerous lesion."
            },
            "diagnosis_pl_treatment_select___laser_resection": {
                "description": "Indicates if the participant has undergone laser resection as treatment for their precancerous lesion."
            },
            "diagnosis_pl_treatment_select___laser_ablation": {
                "description": "Indicates if the participant has undergone laser ablation as treatment for their precancerous lesion."
            },
            "diagnosis_pl_treatment_select___microlaryngeal_surgery_without_laser": {
                "description": "Indicates if the participant has undergone microlaryngeal surgery without laser as treatment for their precancerous lesion."
            },
            "diagnosis_pl_treatment_select___radiotherapy_persistent_or_recurrent_lesions": {
                "description": "Indicates if the participant has undergone radiotherapy for persistent or recurrent lesions."
            },
            "diagnosis_pl_treatment_select___voice_or_speech_therapy": {
                "description": "Indicates if the participant has undergone voice or speech therapy as treatment for their precancerous lesion."
            },
            "diagnosis_pl_treatment_select___other": {
                "description": "Indicates if the participant has undergone other treatments for their precancerous lesion."
            },
            "diagnosis_pl_ds": {
                "question": {
                    "en": "What is the diagnosis?\n(Select all that apply)."
                },
                "datatype": [
                    "xsd:string"
                ],
                "choices": [
                    {
                        "name": {
                            "en": "Keratosis"
                        },
                        "value": "keratosis"
                    },
                    {
                        "name": {
                            "en": "Leukoplakia"
                        },
                        "value": "leukoplakia"
                    },
                    {
                        "name": {
                            "en": "Erythroplakia"
                        },
                        "value": "erythroplakia"
                    },
                    {
                        "name": {
                            "en": "Other"
                        },
                        "value": "other"
                    }
                ],
                "termURL": "https://raw.githubusercontent.com/sensein/b2ai-redcap2rs/24cbb461c2ff6556f047dd4bc1275b4b08d52eb8/activities/d_voice_precancerous_lesions/items/diagnosis_pl_ds",
                "valueType": [
                    "xsd:string"
                ]
            },
            "diagnosis_pl_etiology": {
                "question": {
                    "en": "Does the patient have the following risk factors?\n(Select all that apply)."
                },
                "datatype": [
                    "xsd:string"
                ],
                "choices": [
                    {
                        "name": {
                            "en": "Past or present smoking"
                        },
                        "value": "past_or_present_smoking"
                    },
                    {
                        "name": {
                            "en": "Laryngopharyngeal reflux"
                        },
                        "value": "laryngopharyngeal_reflux"
                    },
                    {
                        "name": {
                            "en": "Other irritants"
                        },
                        "value": "other_irritants"
                    }
                ],
                "termURL": "https://raw.githubusercontent.com/sensein/b2ai-redcap2rs/24cbb461c2ff6556f047dd4bc1275b4b08d52eb8/activities/d_voice_precancerous_lesions/items/diagnosis_pl_etiology",
                "valueType": [
                    "xsd:string"
                ]
            },
            "diagnosis_pl_ds_ll": {
                "question": {
                    "en": "Location of lesion(s)\n(Select all that apply)."
                },
                "datatype": [
                    "xsd:string"
                ],
                "choices": [
                    {
                        "name": {
                            "en": "Right vocal fold"
                        },
                        "value": "right_vocal_fold"
                    },
                    {
                        "name": {
                            "en": "Left vocal fold"
                        },
                        "value": "left_vocal_fold"
                    },
                    {
                        "name": {
                            "en": "Both vocal folds"
                        },
                        "value": "both_vocal_folds"
                    },
                    {
                        "name": {
                            "en": "Ventricular folds (right or left)"
                        },
                        "value": "ventricular_folds"
                    },
                    {
                        "name": {
                            "en": "Subglottal areas"
                        },
                        "value": "subglottal_areas"
                    }
                ],
                "termURL": "https://raw.githubusercontent.com/sensein/b2ai-redcap2rs/24cbb461c2ff6556f047dd4bc1275b4b08d52eb8/activities/d_voice_precancerous_lesions/items/diagnosis_pl_ds_ll",
                "valueType": [
                    "xsd:string"
                ]
            },
            "diagnosis_pl_treatment_select": {
                "question": {
                    "en": "Select all that apply:"
                },
                "datatype": [
                    "xsd:string"
                ],
                "choices": [
                    {
                        "name": {
                            "en": "Surveillance only (previous diagnosis)"
                        },
                        "value": "surveillance_only"
                    },
                    {
                        "name": {
                            "en": "Laser resection"
                        },
                        "value": "laser_resection"
                    },
                    {
                        "name": {
                            "en": "Laser ablation"
                        },
                        "value": "laser_ablation"
                    },
                    {
                        "name": {
                            "en": "Microlaryngeal surgery without laser"
                        },
                        "value": "microlaryngeal_surgery_without_laser"
                    },
                    {
                        "name": {
                            "en": "Radiotherapy for persistent or recurrent lesions"
                        },
                        "value": "radiotherapy_persistent_or_recurrent_lesions"
                    },
                    {
                        "name": {
                            "en": "Voice/speech therapy"
                        },
                        "value": "voice_or_speech_therapy"
                    },
                    {
                        "name": {
                            "en": "Other"
                        },
                        "value": "other"
                    }
                ],
                "termURL": "https://raw.githubusercontent.com/sensein/b2ai-redcap2rs/24cbb461c2ff6556f047dd4bc1275b4b08d52eb8/activities/d_voice_precancerous_lesions/items/diagnosis_pl_treatment_select",
                "valueType": [
                    "xsd:string"
                ]
            },
            "diagnosis_pl_ds_k": {
                "description": {
                    "en": "Keratosis"
                },
                "question": {
                    "en": "Keratosis"
                },
                "datatype": [
                    "xsd:string"
                ],
                "termURL": "https://raw.githubusercontent.com/sensein/b2ai-redcap2rs/61278c480b3a82f24b189119bf97e112e608d114/activities/d_voice_precancerous_lesions/items/diagnosis_pl_ds_k",
                "choices": [
                    {
                        "name": {
                            "en": "With dysplasia"
                        },
                        "value": "withDysplasia"
                    },
                    {
                        "name": {
                            "en": "Without dysplasia"
                        },
                        "value": "withoutDysplasia"
                    }
                ],
                "valueType": [
                    "xsd:string"
                ]
            },
            "diagnosis_pl_ds_k_wd_g": {
                "description": {
                    "en": "Keratosis with dysplasia"
                },
                "question": {
                    "en": "Keratosis with dysplasia"
                },
                "datatype": [
                    "xsd:string"
                ],
                "termURL": "https://raw.githubusercontent.com/sensein/b2ai-redcap2rs/61278c480b3a82f24b189119bf97e112e608d114/activities/d_voice_precancerous_lesions/items/diagnosis_pl_ds_k_wd_g",
                "choices": [
                    {
                        "name": {
                            "en": "Low grade"
                        },
                        "value": "lowGrade"
                    },
                    {
                        "name": {
                            "en": "Moderate grade"
                        },
                        "value": "moderateGrade"
                    },
                    {
                        "name": {
                            "en": "High grade"
                        },
                        "value": "highGrade"
                    }
                ],
                "valueType": [
                    "xsd:string"
                ]
            }
        }
    }
}
